GauAPIs/Molecule.py
GauAPIs/New_Calculator.py
GauAPIs/__init__.py
GauAPIs/main.py
GauAPIs-3.0.1.dist-info/LICENSE.txt
GauAPIs-3.0.1.dist-info/METADATA
GauAPIs-3.0.1.dist-info/WHEEL
GauAPIs-3.0.1.dist-info/entry_points.txt
GauAPIs-3.0.1.dist-info/top_level.txt
GauAPIs-3.0.1.dist-info/RECORD
