Metadata-Version: 2.1
Name: GauAPIs
Version: 3.0.1
Summary: APIs for Gaussian running other calculators through External
Home-page: https://github.com/SamYToeL/APIs
Author: Sam Yunteng Liao
Author-email: lmasgne@gmail.com
License: MIT
Keywords: Gaussian--external python APIs
Platform: linux
License-File: LICENSE.txt
Requires-Dist: numpy
